bot/__main__.py
bot/analysis.py
bot/config.py
bot/email_handler.py
bot/monitoring.py
bot/orchestrator.py
bot/reco_api.py
bot/slack_bot.py
bot/slack_events_endpoint.py
bot/slack_events_handler.py
bot/slack_handler.py
bot/__pycache__/utils/logger.py
bot/utils/__init__.py
bot/utils/logger.py
parser/__init__.py
parser/nlp_utils.py
parser/pdf_parser.py
pptx_generator/__init__.py
pptx_generator/slide_builder.py
reco/__init__.py
reco/generator.py
reco/models.py
utils/__init__.py
utils/logger.py
revolver_ai_bot-0.2.7.dist-info/METADATA
revolver_ai_bot-0.2.7.dist-info/WHEEL
revolver_ai_bot-0.2.7.dist-info/top_level.txt
revolver_ai_bot-0.2.7.dist-info/RECORD
