Metadata-Version: 2.4
Name: revolver_ai_bot
Version: 0.2.7
Summary: Revolver AI Bot
Author-email: Romeo Cavazza <romeo@example.com>
Requires-Python: >=3.10
Requires-Dist: openai>=0.27.0
Requires-Dist: python-dotenv>=1.0.0
Requires-Dist: python-pptx>=0.6.21
Requires-Dist: pdfplumber>=0.11.6
Requires-Dist: pydantic>=2.11.4
Requires-Dist: jsonschema>=4.23.0
Requires-Dist: requests>=2.32.3
Provides-Extra: dev
Requires-Dist: black>=24.3.0; extra == "dev"
Requires-Dist: flake8>=6.1.0; extra == "dev"
Requires-Dist: isort>=5.13.2; extra == "dev"
Requires-Dist: pytest>=8.3.0; extra == "dev"
Requires-Dist: pytest-cov>=4.1.0; extra == "dev"
Requires-Dist: pytest-mock>=3.12.0; extra == "dev"
Requires-Dist: mypy>=1.9.0; extra == "dev"
Requires-Dist: ipython>=8.20.0; extra == "dev"
Requires-Dist: python-dotenv>=1.0.1; extra == "dev"
